README.rst
setup.py
everyplay/__init__.py
everyplay/client.py
everyplay/hashconversions.py
everyplay/request.py
everyplay/resource.py
everyplay.egg-info/PKG-INFO
everyplay.egg-info/SOURCES.txt
everyplay.egg-info/dependency_links.txt
everyplay.egg-info/requires.txt
everyplay.egg-info/top_level.txt