Metadata-Version: 1.1
Name: everyplay
Version: 0.3.6
Summary: A friendly wrapper library for the Everyplay API
Home-page: https://github.com/Everyplay/everyplay-python
Author: Matti Savolainen
Author-email: matti@applifier.com
License: BSD
Platform: UNKNOWN
Classifier: Development Status :: 4 - Beta
Classifier: Intended Audience :: Developers
Classifier: License :: OSI Approved :: BSD License
Classifier: Operating System :: OS Independent
Classifier: Programming Language :: Python
Classifier: Topic :: Internet
Classifier: Topic :: Software Development :: Libraries :: Python Modules
